{
  "nodos": {
    "1": {
      "x": 0,
      "y": 0,
      "restricciones": [
        1,
        1
      ]
    },
    "2": {
      "x": 6.5,
      "y": 0,
      "restricciones": [
        0,
        1
      ]
    },
    "3": {
      "x": 6.5,
      "y": 3.5,
      "restricciones": [
        0,
        1
      ]
    },
    "4": {
      "x": 0,
      "y": 3.5,
      "restricciones": [
        1,
        1
      ]
    }
  },
  "elementos": {
    "1": {
      "nodo_i": 1,
      "nodo_j": 2,
      "E": 200000,
      "A": 0.02
    },
    "2": {
      "nodo_i": 2,
      "nodo_j": 3,
      "E": 200000,
      "A": 0.02
    },
    "3": {
      "nodo_i": 3,
      "nodo_j": 4,
      "E": 200000,
      "A": 0.02
    },
    "4": {
      "nodo_i": 4,
      "nodo_j": 1,
      "E": 200000,
      "A": 0.02
    }
  },
  "cargas": [
    {
      "tipo": "distribuida",
      "elemento": 4,
      "valor": 6.0
    }
  ]
}